[
  {
    "timestamp": "2023-02-16T19:56:04.662387431Z",
    "schedulingLatency": 0,
    "initializedLatency": 0,
    "containersReadyLatency": 1337,
    "podReadyLatency": 1337,
    "metricName": "podLatencyMeasurement",
    "jobName": "cluster-density",
    "jobConfig": {
      "jobIterations": 2,
      "jobIterationDelay": 0,
      "jobPause": 0,
      "name": "cluster-density",
      "objects": null,
      "jobType": "create",
      "qps": 20,
      "burst": 20,
      "namespace": "cluster-density",
      "waitFor": [],
      "maxWaitTimeout": 10800000000000,
      "waitForDeletion": true,
      "podWait": false,
      "waitWhenFinished": true,
      "cleanup": true,
      "namespacedIterations": true,
      "verifyObjects": true,
      "errorOnVerify": true,
      "preLoadImages": true,
      "preLoadPeriod": 60000000000,
      "churn": false,
      "churnPercent": 10,
      "churnDuration": 3600000000000,
      "churnDelay": 300000000000
    },
    "uuid": "a56bcf7c-13b0-4a97-be53-f3ed5817d60b",
    "namespace": "cluster-density-2",
    "podName": "deployment-1pod-2-76f967d4b4-ltpfd",
    "nodeName": "kind-worker2"
  },
  {
    "timestamp": "2023-02-16T19:56:04.715039466Z",
    "schedulingLatency": 0,
    "initializedLatency": 0,
    "containersReadyLatency": 1284,
    "podReadyLatency": 1284,
    "metricName": "podLatencyMeasurement",
    "jobName": "cluster-density",
    "jobConfig": {
      "jobIterations": 2,
      "jobIterationDelay": 0,
      "jobPause": 0,
      "name": "cluster-density",
      "objects": null,
      "jobType": "create",
      "qps": 20,
      "burst": 20,
      "namespace": "cluster-density",
      "waitFor": [],
      "maxWaitTimeout": 10800000000000,
      "waitForDeletion": true,
      "podWait": false,
      "waitWhenFinished": true,
      "cleanup": true,
      "namespacedIterations": true,
      "verifyObjects": true,
      "errorOnVerify": true,
      "preLoadImages": true,
      "preLoadPeriod": 60000000000,
      "churn": false,
      "churnPercent": 10,
      "churnDuration": 3600000000000,
      "churnDelay": 300000000000
    },
    "uuid": "a56bcf7c-13b0-4a97-be53-f3ed5817d60b",
    "namespace": "cluster-density-2",
    "podName": "deployment-1pod-1-569d46c9fc-v2r5m",
    "nodeName": "kind-worker2"
  },
  {
    "timestamp": "2023-02-16T19:56:04.225053426Z",
    "schedulingLatency": 0,
    "initializedLatency": 0,
    "containersReadyLatency": 0,
    "podReadyLatency": 0,
    "metricName": "podLatencyMeasurement",
    "jobName": "cluster-density",
    "jobConfig": {
      "jobIterations": 2,
      "jobIterationDelay": 0,
      "jobPause": 0,
      "name": "cluster-density",
      "objects": null,
      "jobType": "create",
      "qps": 20,
      "burst": 20,
      "namespace": "cluster-density",
      "waitFor": [],
      "maxWaitTimeout": 10800000000000,
      "waitForDeletion": true,
      "podWait": false,
      "waitWhenFinished": true,
      "cleanup": true,
      "namespacedIterations": true,
      "verifyObjects": true,
      "errorOnVerify": true,
      "preLoadImages": true,
      "preLoadPeriod": 60000000000,
      "churn": false,
      "churnPercent": 10,
      "churnDuration": 3600000000000,
      "churnDelay": 300000000000
    },
    "uuid": "a56bcf7c-13b0-4a97-be53-f3ed5817d60b",
    "namespace": "cluster-density-1",
    "podName": "deployment-2pod-1-69f556fccc-wtdvw",
    "nodeName": "kind-worker2"
  },
  {
    "timestamp": "2023-02-16T19:56:04.225769622Z",
    "schedulingLatency": 0,
    "initializedLatency": 0,
    "containersReadyLatency": 774,
    "podReadyLatency": 774,
    "metricName": "podLatencyMeasurement",
    "jobName": "cluster-density",
    "jobConfig": {
      "jobIterations": 2,
      "jobIterationDelay": 0,
      "jobPause": 0,
      "name": "cluster-density",
      "objects": null,
      "jobType": "create",
      "qps": 20,
      "burst": 20,
      "namespace": "cluster-density",
      "waitFor": [],
      "maxWaitTimeout": 10800000000000,
      "waitForDeletion": true,
      "podWait": false,
      "waitWhenFinished": true,
      "cleanup": true,
      "namespacedIterations": true,
      "verifyObjects": true,
      "errorOnVerify": true,
      "preLoadImages": true,
      "preLoadPeriod": 60000000000,
      "churn": false,
      "churnPercent": 10,
      "churnDuration": 3600000000000,
      "churnDelay": 300000000000
    },
    "uuid": "a56bcf7c-13b0-4a97-be53-f3ed5817d60b",
    "namespace": "cluster-density-1",
    "podName": "deployment-1pod-1-569d46c9fc-4pszd",
    "nodeName": "kind-worker"
  },
  {
    "timestamp": "2023-02-16T19:56:04.226090083Z",
    "schedulingLatency": 0,
    "initializedLatency": 0,
    "containersReadyLatency": 773,
    "podReadyLatency": 773,
    "metricName": "podLatencyMeasurement",
    "jobName": "cluster-density",
    "jobConfig": {
      "jobIterations": 2,
      "jobIterationDelay": 0,
      "jobPause": 0,
      "name": "cluster-density",
      "objects": null,
      "jobType": "create",
      "qps": 20,
      "burst": 20,
      "namespace": "cluster-density",
      "waitFor": [],
      "maxWaitTimeout": 10800000000000,
      "waitForDeletion": true,
      "podWait": false,
      "waitWhenFinished": true,
      "cleanup": true,
      "namespacedIterations": true,
      "verifyObjects": true,
      "errorOnVerify": true,
      "preLoadImages": true,
      "preLoadPeriod": 60000000000,
      "churn": false,
      "churnPercent": 10,
      "churnDuration": 3600000000000,
      "churnDelay": 300000000000
    },
    "uuid": "a56bcf7c-13b0-4a97-be53-f3ed5817d60b",
    "namespace": "cluster-density-1",
    "podName": "deployment-1pod-2-76f967d4b4-jlldz",
    "nodeName": "kind-worker"
  },
  {
    "timestamp": "2023-02-16T19:56:04.231437363Z",
    "schedulingLatency": 0,
    "initializedLatency": 0,
    "containersReadyLatency": 768,
    "podReadyLatency": 768,
    "metricName": "podLatencyMeasurement",
    "jobName": "cluster-density",
    "jobConfig": {
      "jobIterations": 2,
      "jobIterationDelay": 0,
      "jobPause": 0,
      "name": "cluster-density",
      "objects": null,
      "jobType": "create",
      "qps": 20,
      "burst": 20,
      "namespace": "cluster-density",
      "waitFor": [],
      "maxWaitTimeout": 10800000000000,
      "waitForDeletion": true,
      "podWait": false,
      "waitWhenFinished": true,
      "cleanup": true,
      "namespacedIterations": true,
      "verifyObjects": true,
      "errorOnVerify": true,
      "preLoadImages": true,
      "preLoadPeriod": 60000000000,
      "churn": false,
      "churnPercent": 10,
      "churnDuration": 3600000000000,
      "churnDelay": 300000000000
    },
    "uuid": "a56bcf7c-13b0-4a97-be53-f3ed5817d60b",
    "namespace": "cluster-density-1",
    "podName": "deployment-2pod-1-69f556fccc-sjgpp",
    "nodeName": "kind-worker"
  },
  {
    "timestamp": "2023-02-16T19:56:04.56843451Z",
    "schedulingLatency": 0,
    "initializedLatency": 0,
    "containersReadyLatency": 2431,
    "podReadyLatency": 2431,
    "metricName": "podLatencyMeasurement",
    "jobName": "cluster-density",
    "jobConfig": {
      "jobIterations": 2,
      "jobIterationDelay": 0,
      "jobPause": 0,
      "name": "cluster-density",
      "objects": null,
      "jobType": "create",
      "qps": 20,
      "burst": 20,
      "namespace": "cluster-density",
      "waitFor": [],
      "maxWaitTimeout": 10800000000000,
      "waitForDeletion": true,
      "podWait": false,
      "waitWhenFinished": true,
      "cleanup": true,
      "namespacedIterations": true,
      "verifyObjects": true,
      "errorOnVerify": true,
      "preLoadImages": true,
      "preLoadPeriod": 60000000000,
      "churn": false,
      "churnPercent": 10,
      "churnDuration": 3600000000000,
      "churnDelay": 300000000000
    },
    "uuid": "a56bcf7c-13b0-4a97-be53-f3ed5817d60b",
    "namespace": "cluster-density-2",
    "podName": "deployment-2pod-1-69f556fccc-xwv62",
    "nodeName": "kind-worker2"
  },
  {
    "timestamp": "2023-02-16T19:56:04.572373754Z",
    "schedulingLatency": 0,
    "initializedLatency": 0,
    "containersReadyLatency": 1427,
    "podReadyLatency": 1427,
    "metricName": "podLatencyMeasurement",
    "jobName": "cluster-density",
    "jobConfig": {
      "jobIterations": 2,
      "jobIterationDelay": 0,
      "jobPause": 0,
      "name": "cluster-density",
      "objects": null,
      "jobType": "create",
      "qps": 20,
      "burst": 20,
      "namespace": "cluster-density",
      "waitFor": [],
      "maxWaitTimeout": 10800000000000,
      "waitForDeletion": true,
      "podWait": false,
      "waitWhenFinished": true,
      "cleanup": true,
      "namespacedIterations": true,
      "verifyObjects": true,
      "errorOnVerify": true,
      "preLoadImages": true,
      "preLoadPeriod": 60000000000,
      "churn": false,
      "churnPercent": 10,
      "churnDuration": 3600000000000,
      "churnDelay": 300000000000
    },
    "uuid": "a56bcf7c-13b0-4a97-be53-f3ed5817d60b",
    "namespace": "cluster-density-2",
    "podName": "deployment-2pod-1-69f556fccc-cfxpg",
    "nodeName": "kind-worker"
  }
]
